tester.py
py_metarium_listener/__init__.py
py_metarium_listener/arikuri/__init__.py
py_metarium_listener/arikuri/arikuri_listener.py
py_metarium_listener/base/__init__.py
py_metarium_listener/base/base_listener.py
py_metarium_listener/blocks/__init__.py
py_metarium_listener/blocks/listener.py
py_metarium_listener/topic_listener/__init__.py
py_metarium_listener/topic_listener/status_listener.py
py_metarium_listener/utils/__init__.py
py_metarium_listener/utils/extrinsic/__init__.py
py_metarium_listener/utils/extrinsic/call.py
py_metarium_listener/utils/object/__init__.py
py_metarium_listener/utils/object/arikuri.py
py_metarium_listener/utils/object/scribe.py
py_metarium_listener/utils/object/topic.py
py_metarium_listener/utils/object/topic_listener.py
py_metarium_listener/utils/query/__init__.py
py_metarium_listener/utils/query/base.py
py_metarium_listener-0.0.2.35.dist-info/LICENSE
py_metarium_listener-0.0.2.35.dist-info/METADATA
py_metarium_listener-0.0.2.35.dist-info/WHEEL
py_metarium_listener-0.0.2.35.dist-info/top_level.txt
py_metarium_listener-0.0.2.35.dist-info/RECORD
